<?xml version="1.0"?>
<!--
 /**
 * GoMage Slider Extension
 *
 * @category     Extension
 * @copyright    Copyright (c) 2010-2014 GoMage (http://www.gomage.com)
 * @author       GoMage
 * @license      http://www.gomage.com/license-agreement/  Single domain license
 * @terms of use http://www.gomage.com/terms-of-use
 * @version      Release: 1.1
 */ 
 -->
<config>
    <acl>
        <resources>
            <admin>
                <children>
                    <system>
                        <children>
                            <config>
                                <children>
                                    <gomage_slider/>
                                </children>
                            </config>
                        </children>
                    </system>
                </children>
            </admin>
        </resources>
    </acl>
    <acl>
        <resources>
            <admin>
                <children>
                    <system>
                        <children>
                            <config>
                                <children>
                                    <gomage_slider/>
                                </children>
                            </config>
                        </children>
                    </system>
                </children>
            </admin>
        </resources>
    </acl>
    <acl>
        <resources>
            <admin>
                <children>
                    <cms>
                        <children>                                                    
                           <gomage_slider/>                    
                        </children>
                    </cms>
                </children>
            </admin>
        </resources>
    </acl>
    <acl>
        <resources>
            <admin>
                <children>
                    <system>
                        <children>
                            <config>
                                <children>
                                    <gomage_notification>
                                        <title>GoMage - Notifications</title>
                                    </gomage_notification>
                                </children>
                            </config>
                        </children>
                    </system>
                </children>
            </admin>
        </resources>
    </acl>
</config>
